BingeWatcher/__init__.py
BingeWatcher/main.py
bingewatcher-0.0.4.dist-info/METADATA
bingewatcher-0.0.4.dist-info/WHEEL
bingewatcher-0.0.4.dist-info/entry_points.txt
bingewatcher-0.0.4.dist-info/licenses/LICENCE
bingewatcher-0.0.4.dist-info/RECORD
